SPACEtomo/CLI.py
SPACEtomo/GUI.py
SPACEtomo/__init__.py
SPACEtomo/config.py
SPACEtomo/run.py
SPACEtomo/run_manual.py
SPACEtomo/run_monitor.py
SPACEtomo/run_nnUNet.py
SPACEtomo/run_prepTargets.py
SPACEtomo/setup_config.py
SPACEtomo/setup_model.py
SPACEtomo/SerialEM_scripts/SPACEtomo_lamellaDetectionGUI.py
SPACEtomo/SerialEM_scripts/SPACEtomo_manMap.py
SPACEtomo/SerialEM_scripts/SPACEtomo_prepareTargets.py
SPACEtomo/SerialEM_scripts/SPACEtomo_run.py
SPACEtomo/SerialEM_scripts/SPACEtomo_targetSelectionGUI.py
SPACEtomo/SerialEM_scripts/__init__.py
SPACEtomo/modules/__init__.py
SPACEtomo/modules/buf.py
SPACEtomo/modules/ext.py
SPACEtomo/modules/geo.py
SPACEtomo/modules/ima.py
SPACEtomo/modules/mma.py
SPACEtomo/modules/mod_wg.py
SPACEtomo/modules/nav.py
SPACEtomo/modules/scope.py
SPACEtomo/modules/sem.py
SPACEtomo/modules/tgt.py
SPACEtomo/modules/utils.py
SPACEtomo/modules/utils_sem.py
SPACEtomo/modules/dummy/__init__.py
SPACEtomo/modules/dummy/buf.py
SPACEtomo/modules/dummy/scope.py
SPACEtomo/modules/dummy/utils_sem.py
SPACEtomo/modules/gui/__init__.py
SPACEtomo/modules/gui/flm.py
SPACEtomo/modules/gui/gui.py
SPACEtomo/modules/gui/lam_sel.py
SPACEtomo/modules/gui/map.py
SPACEtomo/modules/gui/menu.py
SPACEtomo/modules/gui/plot.py
SPACEtomo/modules/gui/tgt_sel.py
SPACEtomo/modules/gui/thmb.py
spacetomo-1.3.0.dist-info/licenses/LICENSE
spacetomo-1.3.0.dist-info/METADATA
spacetomo-1.3.0.dist-info/WHEEL
spacetomo-1.3.0.dist-info/entry_points.txt
spacetomo-1.3.0.dist-info/top_level.txt
spacetomo-1.3.0.dist-info/RECORD
