Metadata-Version: 2.4
Name: SPACEtomo
Version: 1.3.0
Summary: Smart Parallel Automated Cryo Electron tomography (SPACEtomo) is a package that - together with SerialEM - completely automates the cryoET data acquisition workflow.
Home-page: https://github.com/eisfabian/SPACEtomo
Maintainer: Fabian Eisenstein
Maintainer-email: Fabian Eisenstein <spacetomo.help@gmail.com>
License:                     GNU GENERAL PUBLIC LICENSE
Project-URL: Homepage, https://github.com/eisfabian/SPACEtomo
Project-URL: Documentation, https://github.com/eisfabian/SPACEtomo/blob/main/README.md
Project-URL: Repository, https://github.com/eisfabian/SPACEtomo
Project-URL: Issues, https://github.com/eisfabian/SPACEtomo/issues
Keywords: SPACEtomo,cryoET,tomography,electron-tomography,SerialEM
Requires-Python: >=3.6,!=3.7.*,!=3.8.*,!=3.10.*
License-File: LICENSE
Requires-Dist: matplotlib>=3.5; python_version >= "3.9"
Requires-Dist: mrcfile>=1.5.0; python_version >= "3.9"
Requires-Dist: numpy>=1.26.4; python_version >= "3.9"
Requires-Dist: Pillow>=10.4.0; python_version >= "3.9"
Requires-Dist: scipy>=1.12.0; python_version >= "3.9"
Requires-Dist: scikit-image>=0.22.0; python_version >= "3.9"
Requires-Dist: matplotlib>=3.3; python_version < "3.7"
Requires-Dist: mrcfile>=1.5; python_version < "3.7"
Requires-Dist: numpy>=1.19; python_version < "3.7"
Requires-Dist: Pillow>=8.0; python_version < "3.7"
Requires-Dist: scipy>=1.5; python_version < "3.7"
Requires-Dist: scikit-image>=0.17; python_version < "3.7"
Requires-Dist: imageio==2.15.0; python_version < "3.7"
Provides-Extra: gui
Requires-Dist: dearpygui>=1.10.0; python_version >= "3.9" and extra == "gui"
Provides-Extra: predict
Requires-Dist: torch>=2.2.0; python_version >= "3.9" and extra == "predict"
Requires-Dist: torchvision>=0.17.0; python_version >= "3.9" and extra == "predict"
Requires-Dist: nnunetv2>=2.2.1; python_version >= "3.9" and extra == "predict"
Requires-Dist: ultralytics>=8.1.12; python_version >= "3.10" and extra == "predict"
Requires-Dist: ultralytics<8.3.10,>=8.1.12; python_version == "3.9" and extra == "predict"
Dynamic: home-page
Dynamic: license-file
Dynamic: maintainer
Dynamic: requires-python
